pplyz/__init__.py
pplyz/cli.py
pplyz/config.py
pplyz/llm_client.py
pplyz/processor.py
pplyz/schemas.py
pplyz/settings.py
pplyz/utils.py
pplyz-0.1.5.dist-info/licenses/LICENSE
pplyz-0.1.5.dist-info/METADATA
pplyz-0.1.5.dist-info/WHEEL
pplyz-0.1.5.dist-info/entry_points.txt
pplyz-0.1.5.dist-info/top_level.txt
pplyz-0.1.5.dist-info/RECORD
