Metadata-Version: 2.4
Name: pplyz
Version: 0.1.5
Summary: Add LLM-generated columns to CSVs.
Requires-Python: >=3.12
License-File: LICENSE
Requires-Dist: litellm>=1.0.0
Requires-Dist: pandas>=2.2.0
Requires-Dist: prompt-toolkit>=3.0.0
Requires-Dist: tenacity>=8.2.0
Requires-Dist: pydantic>=2.0.0
Provides-Extra: dev
Requires-Dist: build>=1.2.2; extra == "dev"
Requires-Dist: pre-commit>=4.3.0; extra == "dev"
Requires-Dist: pytest>=8.4.2; extra == "dev"
Requires-Dist: pytest-cov>=7.0.0; extra == "dev"
Requires-Dist: pytest-mock>=3.15.1; extra == "dev"
Requires-Dist: twine>=5.1.1; extra == "dev"
Requires-Dist: ruff>=0.14.2; extra == "dev"
Dynamic: license-file
